dotup/__init__.py
dotup-0.3.2.dist-info/entry_points.txt
dotup-0.3.2.dist-info/LICENSE
dotup-0.3.2.dist-info/WHEEL
dotup-0.3.2.dist-info/METADATA
dotup-0.3.2.dist-info/RECORD
