Metadata-Version: 2.1
Name: dotup
Version: 0.3.2
Summary: Symlink your dotfiles with ease.
Home-page: https://github.com/audiolion/dotup
License: UNKNOWN
Keywords: dotfiles,cli,symlink,updater,update
Author: Ryan Castner
Author-email: castner.rr@gmail.com
Requires-Python: >=3.6,<4.0
Classifier: Programming Language :: Python :: 3
Classifier: Programming Language :: Python :: 3.6
Classifier: Programming Language :: Python :: 3.7
Requires-Dist: click (>=7.0,<8.0)
Requires-Dist: crayons (>=0.1.2,<0.2.0)
Project-URL: Repository, https://github.com/audiolion/dotup
